yafi/__init__.py
yafi/__main__.py
yafi/battery.py
yafi/battery_limiter.py
yafi/hardware.py
yafi/leds.py
yafi/main.py
yafi/thermals.py
yafi/window.py
yafi/yafi.gresource
yafi-0.7.dist-info/licenses/COPYING
yafi-0.7.dist-info/METADATA
yafi-0.7.dist-info/WHEEL
yafi-0.7.dist-info/entry_points.txt
yafi-0.7.dist-info/top_level.txt
yafi-0.7.dist-info/RECORD
