Metadata-Version: 2.4
Name: yafi
Version: 0.7
Summary: Yet Another Framework Interface
Author: Steve-Tech
License-Expression: GPL-2.0-or-later
Project-URL: Repository, https://github.com/Steve-Tech/YAFI
Project-URL: Issues, https://github.com/Steve-Tech/YAFI/issues
Classifier: Development Status :: 3 - Alpha
Classifier: Intended Audience :: End Users/Desktop
Classifier: Programming Language :: Python :: 3
Classifier: Operating System :: POSIX :: Linux
Classifier: Topic :: System :: Hardware
Requires-Python: >=3.10
License-File: COPYING
Requires-Dist: cros_ec_python>=0.3.0
Requires-Dist: PyGObject
Provides-Extra: lpc
Requires-Dist: portio; extra == "lpc"
Dynamic: license-file
